mixpanel_query/__init__.py
mixpanel_query/auth.py
mixpanel_query/client.py
mixpanel_query/connection.py
mixpanel_query/exceptions.py
mixpanel_query/paginator.py
mixpanel_query/utils.py
mixpanel_query_py-0.1.9.dist-info/DESCRIPTION.rst
mixpanel_query_py-0.1.9.dist-info/METADATA
mixpanel_query_py-0.1.9.dist-info/RECORD
mixpanel_query_py-0.1.9.dist-info/WHEEL
mixpanel_query_py-0.1.9.dist-info/metadata.json
mixpanel_query_py-0.1.9.dist-info/top_level.txt
