Metadata-Version: 2.0
Name: mixpanel-query-py
Version: 0.1.9
Summary: The Python interface to query data from Mixpanel.
Home-page: https://www.github.com/cooncesean/mixpanel-query-py
Author: Sean Coonce, Francis Genet, Patrick McNally, Harry Marr, @robin900
Author-email: cooncesean@gmail.com
License: UNKNOWN
Platform: UNKNOWN
Classifier: Environment :: Web Environment
Classifier: Intended Audience :: Developers
Classifier: License :: OSI Approved :: MIT License
Classifier: Operating System :: OS Independent
Classifier: Programming Language :: Python
Requires-Dist: six
